dj_temporal/__init__.py
dj_temporal-0.1.0.dist-info/WHEEL
dj_temporal-0.1.0.dist-info/METADATA
dj_temporal-0.1.0.dist-info/RECORD
