Metadata-Version: 2.1
Name: dj-temporal
Version: 0.1.0
Summary: 
Author: Igor Polynets
Author-email: polinom100@gmail.com
Requires-Python: >=3.11,<4.0
Classifier: Programming Language :: Python :: 3
Classifier: Programming Language :: Python :: 3.11
Requires-Dist: temporalio (>=1.5.0,<2.0.0)
